datahub/__init__.py
datahub/__main__.py
datahub/entrypoints.py
datahub/py.typed
datahub/api/__init__.py
datahub/api/circuit_breaker/__init__.py
datahub/api/circuit_breaker/assertion_circuit_breaker.py
datahub/api/circuit_breaker/circuit_breaker.py
datahub/api/circuit_breaker/operation_circuit_breaker.py
datahub/api/entities/__init__.py
datahub/api/entities/corpgroup/__init__.py
datahub/api/entities/corpgroup/corpgroup.py
datahub/api/entities/corpuser/__init__.py
datahub/api/entities/corpuser/corpuser.py
datahub/api/entities/datajob/__init__.py
datahub/api/entities/datajob/dataflow.py
datahub/api/entities/datajob/datajob.py
datahub/api/entities/dataprocess/__init__.py
datahub/api/entities/dataprocess/dataprocess_instance.py
datahub/api/entities/dataproduct/__init__.py
datahub/api/entities/dataproduct/dataproduct.py
datahub/api/graphql/__init__.py
datahub/api/graphql/assertion.py
datahub/api/graphql/base.py
datahub/api/graphql/operation.py
datahub/cli/__init__.py
datahub/cli/check_cli.py
datahub/cli/cli_utils.py
datahub/cli/delete_cli.py
datahub/cli/docker_check.py
datahub/cli/docker_cli.py
datahub/cli/exists_cli.py
datahub/cli/get_cli.py
datahub/cli/ingest_cli.py
datahub/cli/json_file.py
datahub/cli/lite_cli.py
datahub/cli/migrate.py
datahub/cli/migration_utils.py
datahub/cli/put_cli.py
datahub/cli/quickstart_versioning.py
datahub/cli/state_cli.py
datahub/cli/telemetry.py
datahub/cli/timeline_cli.py
datahub/cli/specific/__init__.py
datahub/cli/specific/dataproduct_cli.py
datahub/cli/specific/file_loader.py
datahub/cli/specific/group_cli.py
datahub/cli/specific/user_cli.py
datahub/configuration/__init__.py
datahub/configuration/_config_enum.py
datahub/configuration/common.py
datahub/configuration/config_loader.py
datahub/configuration/datetimes.py
datahub/configuration/git.py
datahub/configuration/import_resolver.py
datahub/configuration/kafka.py
datahub/configuration/oauth.py
datahub/configuration/pattern_utils.py
datahub/configuration/pydantic_field_deprecation.py
cdpdev_datahub-0.10.5.dist-info/METADATA
cdpdev_datahub-0.10.5.dist-info/WHEEL
cdpdev_datahub-0.10.5.dist-info/entry_points.txt
cdpdev_datahub-0.10.5.dist-info/top_level.txt
cdpdev_datahub-0.10.5.dist-info/RECORD
